<?xml version="1.0" encoding="UTF-8" standalone="yes"?>
<unit xmlns="http://www.sdml.info/srcML/src" xmlns:cpp="http://www.sdml.info/srcML/cpp" xmlns:PREFIX="http://www.sdml.info/srcML/position" language="C" filename=" /Users/shuruiz/Work/tmpXMLFile//Users/shuruiz/Work/MarlinRepo/IfdefGroundTruth/Marlin/ArduinoAddons/Arduino_1.0.x/libraries/U8glib/utility/u8g_com_raspberrypi_hw_spi.c" PREFIX:tabs="8"><comment type="block" PREFIX:line="1" PREFIX:column="1">/*
  
  u8g_com_raspberrypi_hw_spi.c

  Universal 8bit Graphics Library
  
  Copyright (c) 2012, olikraus@gmail.com
  All rights reserved.

  Redistribution and use in source and binary forms, with or without modification, 
  are permitted provided that the following conditions are met:

  * Redistributions of source code must retain the above copyright notice, this list 
    of conditions and the following disclaimer.
    
  * Redistributions in binary form must reproduce the above copyright notice, this 
    list of conditions and the following disclaimer in the documentation and/or other 
    materials provided with the distribution.

  THIS SOFTWARE IS PROVIDED BY THE COPYRIGHT HOLDERS AND 
  CONTRIBUTORS "AS IS" AND ANY EXPRESS OR IMPLIED WARRANTIES, 
  INCLUDING, BUT NOT LIMITED TO, THE IMPLIED WARRANTIES OF 
  MERCHANTABILITY AND FITNESS FOR A PARTICULAR PURPOSE ARE 
  DISCLAIMED. IN NO EVENT SHALL THE COPYRIGHT HOLDER OR 
  CONTRIBUTORS BE LIABLE FOR ANY DIRECT, INDIRECT, INCIDENTAL, 
  SPECIAL, EXEMPLARY, OR CONSEQUENTIAL DAMAGES (INCLUDING, BUT 
  NOT LIMITED TO, PROCUREMENT OF SUBSTITUTE GOODS OR SERVICES; 
  LOSS OF USE, DATA, OR PROFITS; OR BUSINESS INTERRUPTION) HOWEVER 
  CAUSED AND ON ANY THEORY OF LIABILITY, WHETHER IN CONTRACT, 
  STRICT LIABILITY, OR TORT (INCLUDING NEGLIGENCE OR OTHERWISE) 
  ARISING IN ANY WAY OUT OF THE USE OF THIS SOFTWARE, EVEN IF 
  ADVISED OF THE POSSIBILITY OF SUCH DAMAGE.  
  
  
  Assumes, that 
    MOSI is at PORTB, Pin 3
  and
    SCK is at PORTB, Pin 5

  Update for ATOMIC operation done (01 Jun 2013)
    U8G_ATOMIC_OR(ptr, val)
    U8G_ATOMIC_AND(ptr, val)
    U8G_ATOMIC_START()
    U8G_ATOMIC_END()
 


*/</comment>

<cpp:include PREFIX:line="50" PREFIX:column="1">#<cpp:directive PREFIX:line="50" PREFIX:column="2">include</cpp:directive> <cpp:file PREFIX:line="50" PREFIX:column="10">"u8g.h"</cpp:file></cpp:include>



<cpp:if PREFIX:line="54" PREFIX:column="1">#<cpp:directive PREFIX:line="54" PREFIX:column="2">if</cpp:directive> <expr><call><name PREFIX:line="54" PREFIX:column="5">defined</name><argument_list PREFIX:line="54" PREFIX:column="12">(<argument><expr><name PREFIX:line="54" PREFIX:column="13">U8G_RASPBERRY_PI</name></expr></argument>)</argument_list></call></expr></cpp:if>

<cpp:include PREFIX:line="56" PREFIX:column="1">#<cpp:directive PREFIX:line="56" PREFIX:column="2">include</cpp:directive> <cpp:file PREFIX:line="56" PREFIX:column="10">&lt;wiringPiSPI.h&gt;</cpp:file></cpp:include>
<cpp:include PREFIX:line="57" PREFIX:column="1">#<cpp:directive PREFIX:line="57" PREFIX:column="2">include</cpp:directive> <cpp:file PREFIX:line="57" PREFIX:column="10">&lt;wiringPi.h&gt;</cpp:file></cpp:include>
<cpp:include PREFIX:line="58" PREFIX:column="1">#<cpp:directive PREFIX:line="58" PREFIX:column="2">include</cpp:directive> <cpp:file PREFIX:line="58" PREFIX:column="10">&lt;stdio.h&gt;</cpp:file></cpp:include>
<cpp:include PREFIX:line="59" PREFIX:column="1">#<cpp:directive PREFIX:line="59" PREFIX:column="2">include</cpp:directive> <cpp:file PREFIX:line="59" PREFIX:column="10">&lt;stdlib.h&gt;</cpp:file></cpp:include>
<cpp:include PREFIX:line="60" PREFIX:column="1">#<cpp:directive PREFIX:line="60" PREFIX:column="2">include</cpp:directive> <cpp:file PREFIX:line="60" PREFIX:column="10">&lt;errno.h&gt;</cpp:file></cpp:include>

<function><type><name PREFIX:line="62" PREFIX:column="1">uint8_t</name></type> <name PREFIX:line="62" PREFIX:column="9">u8g_com_raspberrypi_hw_spi_fn</name><parameter_list PREFIX:line="62" PREFIX:column="38">(<param><decl><type><name PREFIX:line="62" PREFIX:column="39">u8g_t</name> *</type><name PREFIX:line="62" PREFIX:column="46">u8g</name></decl></param>, <param><decl><type><name PREFIX:line="62" PREFIX:column="51">uint8_t</name></type> <name PREFIX:line="62" PREFIX:column="59">msg</name></decl></param>, <param><decl><type><name PREFIX:line="62" PREFIX:column="64">uint8_t</name></type> <name PREFIX:line="62" PREFIX:column="72">arg_val</name></decl></param>, <param><decl><type><name PREFIX:line="62" PREFIX:column="81">void</name> *</type><name PREFIX:line="62" PREFIX:column="87">arg_ptr</name></decl></param>)</parameter_list>
<block PREFIX:line="63" PREFIX:column="1">{
  <switch PREFIX:line="64" PREFIX:column="3">switch<condition PREFIX:line="64" PREFIX:column="9">(<expr><name PREFIX:line="64" PREFIX:column="10">msg</name></expr>)</condition>
  <block PREFIX:line="65" PREFIX:column="3">{
    <case PREFIX:line="66" PREFIX:column="5">case <expr><name PREFIX:line="66" PREFIX:column="10">U8G_COM_MSG_STOP</name></expr>:
      <break PREFIX:line="67" PREFIX:column="7">break;</break>
    
    </case><case PREFIX:line="69" PREFIX:column="5">case <expr><name PREFIX:line="69" PREFIX:column="10">U8G_COM_MSG_INIT</name></expr>:
		<comment type="line" PREFIX:line="70" PREFIX:column="17">// check wiringPi setup</comment>
		<if PREFIX:line="71" PREFIX:column="17">if <condition PREFIX:line="71" PREFIX:column="20">(<expr><call><name PREFIX:line="71" PREFIX:column="21">wiringPiSetup</name><argument_list PREFIX:line="71" PREFIX:column="34">()</argument_list></call> == -1</expr>)</condition><then PREFIX:line="71" PREFIX:column="43">
		<block PREFIX:line="72" PREFIX:column="17">{
			<expr_stmt><expr><call><name PREFIX:line="73" PREFIX:column="25">printf</name><argument_list PREFIX:line="73" PREFIX:column="31">(<argument><expr PREFIX:line="73" PREFIX:column="32">"wiringPi-Error\n"</expr></argument>)</argument_list></call></expr>;</expr_stmt>
			<expr_stmt><expr><call><name PREFIX:line="74" PREFIX:column="25">exit</name><argument_list PREFIX:line="74" PREFIX:column="29">(<argument><expr PREFIX:line="74" PREFIX:column="30">1</expr></argument>)</argument_list></call></expr>;</expr_stmt>
		}</block></then></if>

		<if PREFIX:line="77" PREFIX:column="17">if <condition PREFIX:line="77" PREFIX:column="20">(<expr><call><name PREFIX:line="77" PREFIX:column="21">wiringPiSPISetup</name> <argument_list PREFIX:line="77" PREFIX:column="38">(<argument><expr PREFIX:line="77" PREFIX:column="39">0</expr></argument>, <argument><expr PREFIX:line="77" PREFIX:column="42">100000</expr></argument>)</argument_list></call> &lt; 0</expr>)</condition><then PREFIX:line="77" PREFIX:column="54">
		<block PREFIX:line="78" PREFIX:column="17">{
			<expr_stmt><expr><call><name PREFIX:line="79" PREFIX:column="25">printf</name> <argument_list PREFIX:line="79" PREFIX:column="32">(<argument><expr PREFIX:line="79" PREFIX:column="33">"Unable to open SPI device 0: %s\n"</expr></argument>, <argument><expr><call><name PREFIX:line="79" PREFIX:column="70">strerror</name> <argument_list PREFIX:line="79" PREFIX:column="79">(<argument><expr><name PREFIX:line="79" PREFIX:column="80">errno</name></expr></argument>)</argument_list></call></expr></argument>)</argument_list></call></expr> ;</expr_stmt>
			<expr_stmt><expr><call><name PREFIX:line="80" PREFIX:column="25">exit</name> <argument_list PREFIX:line="80" PREFIX:column="30">(<argument><expr PREFIX:line="80" PREFIX:column="31">1</expr></argument>)</argument_list></call></expr> ;</expr_stmt>
		}</block></then></if>
		
		<expr_stmt><expr><call><name PREFIX:line="83" PREFIX:column="17">u8g_SetPIOutput</name><argument_list PREFIX:line="83" PREFIX:column="32">(<argument><expr><name PREFIX:line="83" PREFIX:column="33">u8g</name></expr></argument>, <argument><expr><name PREFIX:line="83" PREFIX:column="38">U8G_PI_RESET</name></expr></argument>)</argument_list></call></expr>;</expr_stmt>
		<expr_stmt><expr><call><name PREFIX:line="84" PREFIX:column="17">u8g_SetPIOutput</name><argument_list PREFIX:line="84" PREFIX:column="32">(<argument><expr><name PREFIX:line="84" PREFIX:column="33">u8g</name></expr></argument>, <argument><expr><name PREFIX:line="84" PREFIX:column="38">U8G_PI_A0</name></expr></argument>)</argument_list></call></expr>;</expr_stmt>

      <break PREFIX:line="86" PREFIX:column="7">break;</break>
    
    </case><case PREFIX:line="88" PREFIX:column="5">case <expr><name PREFIX:line="88" PREFIX:column="10">U8G_COM_MSG_ADDRESS</name></expr>:                     <comment type="block" PREFIX:line="88" PREFIX:column="51">/* define cmd (arg_val = 0) or data mode (arg_val = 1) */</comment>
	  <expr_stmt><expr><call><name PREFIX:line="89" PREFIX:column="11">u8g_SetPILevel</name><argument_list PREFIX:line="89" PREFIX:column="25">(<argument><expr><name PREFIX:line="89" PREFIX:column="26">u8g</name></expr></argument>, <argument><expr><name PREFIX:line="89" PREFIX:column="31">U8G_PI_A0</name></expr></argument>, <argument><expr><name PREFIX:line="89" PREFIX:column="42">arg_val</name></expr></argument>)</argument_list></call></expr>;</expr_stmt>
      <break PREFIX:line="90" PREFIX:column="7">break;</break>

    </case><case PREFIX:line="92" PREFIX:column="5">case <expr><name PREFIX:line="92" PREFIX:column="10">U8G_COM_MSG_CHIP_SELECT</name></expr>:
		<comment type="block" PREFIX:line="93" PREFIX:column="17">/* Done by the SPI hardware */</comment>
      <break PREFIX:line="94" PREFIX:column="7">break;</break>
      
    </case><case PREFIX:line="96" PREFIX:column="5">case <expr><name PREFIX:line="96" PREFIX:column="10">U8G_COM_MSG_RESET</name></expr>:
      <expr_stmt><expr><call><name PREFIX:line="97" PREFIX:column="7">u8g_SetPILevel</name><argument_list PREFIX:line="97" PREFIX:column="21">(<argument><expr><name PREFIX:line="97" PREFIX:column="22">u8g</name></expr></argument>, <argument><expr><name PREFIX:line="97" PREFIX:column="27">U8G_PI_RESET</name></expr></argument>, <argument><expr><name PREFIX:line="97" PREFIX:column="41">arg_val</name></expr></argument>)</argument_list></call></expr>;</expr_stmt>
      <break PREFIX:line="98" PREFIX:column="7">break;</break>
    
    </case><case PREFIX:line="100" PREFIX:column="5">case <expr><name PREFIX:line="100" PREFIX:column="10">U8G_COM_MSG_WRITE_BYTE</name></expr>:
		<expr_stmt><expr><call><name PREFIX:line="101" PREFIX:column="17">wiringPiSPIDataRW</name> <argument_list PREFIX:line="101" PREFIX:column="35">(<argument><expr PREFIX:line="101" PREFIX:column="36">0</expr></argument>, <argument><expr PREFIX:line="101" PREFIX:column="39">&amp;<name PREFIX:line="101" PREFIX:column="40">arg_val</name></expr></argument>, <argument><expr PREFIX:line="101" PREFIX:column="49">1</expr></argument>)</argument_list></call></expr> ;</expr_stmt>
      <break PREFIX:line="102" PREFIX:column="7">break;</break>
    
    </case><case PREFIX:line="104" PREFIX:column="5">case <expr><name PREFIX:line="104" PREFIX:column="10">U8G_COM_MSG_WRITE_SEQ</name></expr>:
		<expr_stmt><expr><call><name PREFIX:line="105" PREFIX:column="17">wiringPiSPIDataRW</name> <argument_list PREFIX:line="105" PREFIX:column="35">(<argument><expr PREFIX:line="105" PREFIX:column="36">0</expr></argument>, <argument><expr><name PREFIX:line="105" PREFIX:column="39">arg_ptr</name></expr></argument>, <argument><expr><name PREFIX:line="105" PREFIX:column="48">arg_val</name></expr></argument>)</argument_list></call></expr>;</expr_stmt>
      <break PREFIX:line="106" PREFIX:column="7">break;</break>

	</case><case PREFIX:line="108" PREFIX:column="9">case <expr><name PREFIX:line="108" PREFIX:column="14">U8G_COM_MSG_WRITE_SEQ_P</name></expr>:
		<expr_stmt><expr><call><name PREFIX:line="109" PREFIX:column="17">wiringPiSPIDataRW</name> <argument_list PREFIX:line="109" PREFIX:column="35">(<argument><expr PREFIX:line="109" PREFIX:column="36">0</expr></argument>, <argument><expr><name PREFIX:line="109" PREFIX:column="39">arg_ptr</name></expr></argument>, <argument><expr><name PREFIX:line="109" PREFIX:column="48">arg_val</name></expr></argument>)</argument_list></call></expr>;</expr_stmt>		
      <break PREFIX:line="110" PREFIX:column="7">break;</break>
  </case>}</block></switch>
  <return PREFIX:line="112" PREFIX:column="3">return <expr PREFIX:line="112" PREFIX:column="10">1</expr>;</return>
}</block></function>

<cpp:else PREFIX:line="115" PREFIX:column="1">#<cpp:directive PREFIX:line="115" PREFIX:column="2">else</cpp:directive></cpp:else>

<function><type><name PREFIX:line="117" PREFIX:column="1">uint8_t</name></type> <name PREFIX:line="117" PREFIX:column="9">u8g_com_raspberrypi_hw_spi_fn</name><parameter_list PREFIX:line="117" PREFIX:column="38">(<param><decl><type><name PREFIX:line="117" PREFIX:column="39">u8g_t</name> *</type><name PREFIX:line="117" PREFIX:column="46">u8g</name></decl></param>, <param><decl><type><name PREFIX:line="117" PREFIX:column="51">uint8_t</name></type> <name PREFIX:line="117" PREFIX:column="59">msg</name></decl></param>, <param><decl><type><name PREFIX:line="117" PREFIX:column="64">uint8_t</name></type> <name PREFIX:line="117" PREFIX:column="72">arg_val</name></decl></param>, <param><decl><type><name PREFIX:line="117" PREFIX:column="81">void</name> *</type><name PREFIX:line="117" PREFIX:column="87">arg_ptr</name></decl></param>)</parameter_list>
<block PREFIX:line="118" PREFIX:column="1">{
  <return PREFIX:line="119" PREFIX:column="3">return <expr PREFIX:line="119" PREFIX:column="10">1</expr>;</return>
}</block></function>

<cpp:endif PREFIX:line="122" PREFIX:column="1">#<cpp:directive PREFIX:line="122" PREFIX:column="2">endif</cpp:directive></cpp:endif>


</unit>
